hls_tools/__init__.py
hls_tools/constants.py
hls_tools-0.0.3.dist-info/LICENSE
hls_tools-0.0.3.dist-info/WHEEL
hls_tools-0.0.3.dist-info/METADATA
hls_tools-0.0.3.dist-info/RECORD
