Metadata-Version: 2.1
Name: hls_tools
Version: 0.0.3
Summary: Tools for working with the Harmonized Landsat Sentinel 2 remote sensing dataset
Author-email: Henry Rodman <henry.rodman@gmail.com>
Requires-Python: >=3.8
Requires-Dist: pystac
Requires-Dist: pystac_client
Requires-Dist: rasterio
Requires-Dist: stackstac
Requires-Dist: xarray
Requires-Dist: black~=23.3 ; extra == "dev"
Requires-Dist: codespell~=2.2 ; extra == "dev"
Requires-Dist: importlib-metadata~=6.6 ; extra == "dev"
Requires-Dist: ipython~=8.12 ; extra == "dev"
Requires-Dist: jupyter~=1.0 ; extra == "dev"
Requires-Dist: mypy~=1.3 ; extra == "dev"
Requires-Dist: packaging~=23.1 ; extra == "dev"
Requires-Dist: pre-commit~=3.3 ; extra == "dev"
Requires-Dist: pylint~=2.17 ; extra == "dev"
Requires-Dist: pytest~=7.3 ; extra == "dev"
Requires-Dist: ruff==0.0.265 ; extra == "dev"
Requires-Dist: types-certifi~=2021.10.8 ; extra == "dev"
Requires-Dist: types-orjson~=3.6 ; extra == "dev"
Requires-Dist: types-python-dateutil~=2.8 ; extra == "dev"
Requires-Dist: types-requests~=2.30 ; extra == "dev"
Requires-Dist: pytest ; extra == "test"
Project-URL: Source, https://github.com/hrodmn/hls-tools
Provides-Extra: dev
Provides-Extra: test
